{"chunk_definitions":[{"chunk_id":"csetup_chunk","chunk_label":"setup","document_id":"1B1515E0","expansion_state":0,"options":{"engine":"r","include":false,"label":"setup"},"row":24,"row_count":1,"visible":true},{"chunk_id":"c77edx37y6us0","chunk_label":"unnamed-chunk-2","document_id":"1B1515E0","expansion_state":0,"options":{"echo":false,"engine":"r","label":"unnamed-chunk-20"},"row":104,"row_count":1,"visible":true}],"chunk_rendered_width":632,"default_chunk_options":{},"doc_write_time":1625410467,"working_dir":null}